{
    "format_version": "1.8.0",
    "minecraft:client_entity": {
        "description": {
            "identifier": "mobarenawq:shop_health",
            "materials": {
                "default": "entity"
            },
            "textures": {
                "default": "textures/entity/shop/health"
            },
            "geometry": {
                "default": "geometry.health"
            },
            "render_controllers": [
                "controller.render.shop"
            ],
            "animations": {
                "idle": "animation.health.idle"
            },
            "animation_controllers": [
                { "idle": "controller.animation.shop" }
            ]
        }
    }
}